README.md
setup.py
imm_source.egg-info/PKG-INFO
imm_source.egg-info/SOURCES.txt
imm_source.egg-info/dependency_links.txt
imm_source.egg-info/top_level.txt
source/__init__.py
source/comment.py
source/excel.py
source/excelwriter.py
source/formatdefinition.py
source/infosheet.py
source/tablesheet.py
source/validation.py